professordriver/__init__.py
professordriver/driver_setup.py
professordriver/data/hlifkpholllijblknnmbfagnkjneagid.crx
professordriver-0.1.0.dist-info/LICENSE
professordriver-0.1.0.dist-info/METADATA
professordriver-0.1.0.dist-info/WHEEL
professordriver-0.1.0.dist-info/top_level.txt
professordriver-0.1.0.dist-info/RECORD
