Metadata-Version: 2.1
Name: professordriver
Version: 0.1.0
Summary: A utility package to set up Selenium WebDriver with custom configurations.
Home-page: https://github.com/yourusername/professordriver
Author: Hovhannes
Author-email: test@harevan.ru
Classifier: Programming Language :: Python :: 3
Classifier: License :: OSI Approved :: MIT License
Classifier: Operating System :: OS Independent
Requires-Python: >=3.6
License-File: LICENSE
Requires-Dist: selenium >=3.141.0
